texnew/__init__.py
texnew/__main__.py
texnew/core.py
texnew/document.py
texnew/error.py
texnew/file.py
texnew/file_mgr.py
texnew/old.py
texnew/parse.py
texnew/parse_old.py
texnew/rpath.py
texnew/scripts.py
texnew/template.py
texnew/test.py
texnew/update.py
texnew-1.13.dist-info/LICENSE
texnew-1.13.dist-info/METADATA
texnew-1.13.dist-info/WHEEL
texnew-1.13.dist-info/entry_points.txt
texnew-1.13.dist-info/top_level.txt
texnew-1.13.dist-info/RECORD
